Metadata-Version: 2.1
Name: Abyss-Shell
Version: 1.0.0
Summary: A very basic package to create shells/menus.
Home-page: UNKNOWN
Author: Marlon Hernández
Author-email: mmarlon.ssantiago@gmail.com
License: MIT
Keywords: Shell
Platform: UNKNOWN
Classifier: Development Status :: 5 - Production/Stable
Classifier: Intended Audience :: Education
Classifier: Operating System :: Microsoft :: Windows :: Windows 10
Classifier: License :: OSI Approved :: MIT License
Classifier: Programming Language :: Python :: 3
License-File: LICENSE.txt
